{"action":{"identity":{"address":"N\u0000sourcecred\u0000core\u0000IDENTITY\u0000kC1tdnb0N7RnWRyRUDJclA\u0000","aliases":[],"id":"kC1tdnb0N7RnWRyRUDJclA","name":"George-Lovegrove","subtype":"USER"},"type":"CREATE_IDENTITY"},"ledgerTimestamp":1627777843157,"uuid":"MAqH2KSlwXAJ9MHQT8dIAQ","version":"1"}
{"action":{"alias":{"address":"N\u0000sourcecred\u0000discord\u0000MEMBER\u0000user\u0000144835871525306368\u0000","description":"discord/George Lovegrove#3020"},"identityId":"kC1tdnb0N7RnWRyRUDJclA","type":"ADD_ALIAS"},"ledgerTimestamp":1627777843157,"uuid":"fmeSzV3RexyFdePpaGR2Eg","version":"1"}
{"action":{"identity":{"address":"N\u0000sourcecred\u0000core\u0000IDENTITY\u0000IYKZ73FA1bacDjr8ydGPcA\u0000","aliases":[],"id":"IYKZ73FA1bacDjr8ydGPcA","name":"Seo4u","subtype":"USER"},"type":"CREATE_IDENTITY"},"ledgerTimestamp":1627777843158,"uuid":"MfvveOTd4eJtEsXFobLa7w","version":"1"}
{"action":{"alias":{"address":"N\u0000sourcecred\u0000discord\u0000MEMBER\u0000user\u0000160981697700036608\u0000","description":"discord/Seo4u#6254"},"identityId":"IYKZ73FA1bacDjr8ydGPcA","type":"ADD_ALIAS"},"ledgerTimestamp":1627777843158,"uuid":"x1pbNnvgzhlTYSvUz4qa4w","version":"1"}
{"action":{"identity":{"address":"N\u0000sourcecred\u0000core\u0000IDENTITY\u0000X8JXQxMHabrOaXvJ7TAbcw\u0000","aliases":[],"id":"X8JXQxMHabrOaXvJ7TAbcw","name":"whitevo","subtype":"USER"},"type":"CREATE_IDENTITY"},"ledgerTimestamp":1627777843158,"uuid":"l3PxGsMR3T5aCawo8D80Ng","version":"1"}
{"action":{"alias":{"address":"N\u0000sourcecred\u0000discord\u0000MEMBER\u0000user\u0000179922222339588096\u0000","description":"discord/whitevo#9715"},"identityId":"X8JXQxMHabrOaXvJ7TAbcw","type":"ADD_ALIAS"},"ledgerTimestamp":1627777843158,"uuid":"Oo3qcmWAPIyKnkIzL8aDaw","version":"1"}
{"action":{"identity":{"address":"N\u0000sourcecred\u0000core\u0000IDENTITY\u0000KG8DXrL14f6o6AKEEQAMag\u0000","aliases":[],"id":"KG8DXrL14f6o6AKEEQAMag","name":"Ren--M-","subtype":"USER"},"type":"CREATE_IDENTITY"},"ledgerTimestamp":1627777843159,"uuid":"EV0V50cjMbaIyGRzCdQ5nQ","version":"1"}
{"action":{"alias":{"address":"N\u0000sourcecred\u0000discord\u0000MEMBER\u0000user\u0000253617981479714816\u0000","description":"discord/Ren&#xE9; M.#5987"},"identityId":"KG8DXrL14f6o6AKEEQAMag","type":"ADD_ALIAS"},"ledgerTimestamp":1627777843159,"uuid":"6AvrG5nSx7yz8xJ2mWiDFA","version":"1"}
{"action":{"identity":{"address":"N\u0000sourcecred\u0000core\u0000IDENTITY\u0000vd5Fdsps1OVFET1W8dIbSA\u0000","aliases":[],"id":"vd5Fdsps1OVFET1W8dIbSA","name":"Phil-K","subtype":"USER"},"type":"CREATE_IDENTITY"},"ledgerTimestamp":1627777843160,"uuid":"yyoWLDmkvrc2RRFpSqA7Gg","version":"1"}
{"action":{"alias":{"address":"N\u0000sourcecred\u0000discord\u0000MEMBER\u0000user\u0000277440896545587200\u0000","description":"discord/Phil K#6595"},"identityId":"vd5Fdsps1OVFET1W8dIbSA","type":"ADD_ALIAS"},"ledgerTimestamp":1627777843160,"uuid":"BQZcR5nio9TzeWVneaTvvg","version":"1"}
{"action":{"identity":{"address":"N\u0000sourcecred\u0000core\u0000IDENTITY\u0000Q8AwrPlPcoPdYG4LIGgJ9g\u0000","aliases":[],"id":"Q8AwrPlPcoPdYG4LIGgJ9g","name":"DanMercurius","subtype":"USER"},"type":"CREATE_IDENTITY"},"ledgerTimestamp":1627777843160,"uuid":"zgIWdyKsnMVTEbVFqoCAzA","version":"1"}
{"action":{"alias":{"address":"N\u0000sourcecred\u0000discord\u0000MEMBER\u0000user\u0000331572987092533248\u0000","description":"discord/DanMercurius#7990"},"identityId":"Q8AwrPlPcoPdYG4LIGgJ9g","type":"ADD_ALIAS"},"ledgerTimestamp":1627777843161,"uuid":"eyTpXc66Ms12x4lP4wFMDA","version":"1"}
{"action":{"identity":{"address":"N\u0000sourcecred\u0000core\u0000IDENTITY\u00004ElGvxbBn4lvRxTQMpTXDA\u0000","aliases":[],"id":"4ElGvxbBn4lvRxTQMpTXDA","name":"Quasar","subtype":"USER"},"type":"CREATE_IDENTITY"},"ledgerTimestamp":1627777843161,"uuid":"9vKWHWwozjEh3Iq5UpzKHw","version":"1"}
{"action":{"alias":{"address":"N\u0000sourcecred\u0000discord\u0000MEMBER\u0000user\u0000346305486829780993\u0000","description":"discord/Quasar#0436"},"identityId":"4ElGvxbBn4lvRxTQMpTXDA","type":"ADD_ALIAS"},"ledgerTimestamp":1627777843161,"uuid":"fA3ndKslbU6x6yflEx7L2g","version":"1"}
{"action":{"identity":{"address":"N\u0000sourcecred\u0000core\u0000IDENTITY\u0000DYl8fOBhX7QB3zdNYXZkWA\u0000","aliases":[],"id":"DYl8fOBhX7QB3zdNYXZkWA","name":"rodrigopacini","subtype":"USER"},"type":"CREATE_IDENTITY"},"ledgerTimestamp":1627777843161,"uuid":"b5mcodPIvEx48RgBBXrZRg","version":"1"}
{"action":{"alias":{"address":"N\u0000sourcecred\u0000discord\u0000MEMBER\u0000user\u0000399912546024554497\u0000","description":"discord/rodrigopacini#6495"},"identityId":"DYl8fOBhX7QB3zdNYXZkWA","type":"ADD_ALIAS"},"ledgerTimestamp":1627777843162,"uuid":"gNDk9GQUQVOa2Oo7XaT2jw","version":"1"}
{"action":{"identity":{"address":"N\u0000sourcecred\u0000core\u0000IDENTITY\u0000oPDxGbCXRKbQ3BgI62Eywg\u0000","aliases":[],"id":"oPDxGbCXRKbQ3BgI62Eywg","name":"Sosha","subtype":"USER"},"type":"CREATE_IDENTITY"},"ledgerTimestamp":1627777843162,"uuid":"ouaDn7voFRNvQ5OoxXBEYA","version":"1"}
{"action":{"alias":{"address":"N\u0000sourcecred\u0000discord\u0000MEMBER\u0000user\u0000403227475523403779\u0000","description":"discord/Sosha#9810"},"identityId":"oPDxGbCXRKbQ3BgI62Eywg","type":"ADD_ALIAS"},"ledgerTimestamp":1627777843162,"uuid":"MUdWMVyx38hygax7XeygrQ","version":"1"}
{"action":{"identity":{"address":"N\u0000sourcecred\u0000core\u0000IDENTITY\u0000Q66yHvh2mV8yNMBhmDbwcQ\u0000","aliases":[],"id":"Q66yHvh2mV8yNMBhmDbwcQ","name":"Decentralized-Reality----DECNT-","subtype":"USER"},"type":"CREATE_IDENTITY"},"ledgerTimestamp":1627777843162,"uuid":"12OBKd77HDXamXx8Odeh8A","version":"1"}
{"action":{"alias":{"address":"N\u0000sourcecred\u0000discord\u0000MEMBER\u0000user\u0000404721685745631255\u0000","description":"discord/Decentralized Reality - [DECNT]#3078"},"identityId":"Q66yHvh2mV8yNMBhmDbwcQ","type":"ADD_ALIAS"},"ledgerTimestamp":1627777843163,"uuid":"Bd9fLldgBfGxgKtjX5qCvA","version":"1"}
{"action":{"identity":{"address":"N\u0000sourcecred\u0000core\u0000IDENTITY\u0000GDrCLXepwSDq1rkzfa1NCQ\u0000","aliases":[],"id":"GDrCLXepwSDq1rkzfa1NCQ","name":"Aidan-R-W--PlayerMint-","subtype":"USER"},"type":"CREATE_IDENTITY"},"ledgerTimestamp":1627777843163,"uuid":"GYEhYmyRF4YOzEI9mtddkg","version":"1"}
{"action":{"alias":{"address":"N\u0000sourcecred\u0000discord\u0000MEMBER\u0000user\u0000538173976715722783\u0000","description":"discord/Aidan R-W (PlayerMint)#8452"},"identityId":"GDrCLXepwSDq1rkzfa1NCQ","type":"ADD_ALIAS"},"ledgerTimestamp":1627777843164,"uuid":"vPr1bNV5eDIzO9tbwFBJKw","version":"1"}
{"action":{"identity":{"address":"N\u0000sourcecred\u0000core\u0000IDENTITY\u0000Vjm6mwvAzg6d9WHE6p5T4A\u0000","aliases":[],"id":"Vjm6mwvAzg6d9WHE6p5T4A","name":"Steven-Aldrich","subtype":"USER"},"type":"CREATE_IDENTITY"},"ledgerTimestamp":1627777843164,"uuid":"h5V9lwfBdIDrDZVwR9srMg","version":"1"}
{"action":{"alias":{"address":"N\u0000sourcecred\u0000discord\u0000MEMBER\u0000user\u0000555460548595286017\u0000","description":"discord/Steven Aldrich#0457"},"identityId":"Vjm6mwvAzg6d9WHE6p5T4A","type":"ADD_ALIAS"},"ledgerTimestamp":1627777843164,"uuid":"QmjB07LN7lkMdyami4IBkA","version":"1"}
{"action":{"identity":{"address":"N\u0000sourcecred\u0000core\u0000IDENTITY\u0000l2CArxS5iVFAmgkVo34Grw\u0000","aliases":[],"id":"l2CArxS5iVFAmgkVo34Grw","name":"jadjei","subtype":"USER"},"type":"CREATE_IDENTITY"},"ledgerTimestamp":1627777843165,"uuid":"uMkeDdN1qacgnKhyzBRCwg","version":"1"}
{"action":{"alias":{"address":"N\u0000sourcecred\u0000discord\u0000MEMBER\u0000user\u0000594691110568198154\u0000","description":"discord/jadjei#4938"},"identityId":"l2CArxS5iVFAmgkVo34Grw","type":"ADD_ALIAS"},"ledgerTimestamp":1627777843165,"uuid":"zMdwBgGCmazPOvVoRYRH5g","version":"1"}
{"action":{"identity":{"address":"N\u0000sourcecred\u0000core\u0000IDENTITY\u0000C9sGGSjXiLkD81eVMeqkqw\u0000","aliases":[],"id":"C9sGGSjXiLkD81eVMeqkqw","name":"VladimirP","subtype":"USER"},"type":"CREATE_IDENTITY"},"ledgerTimestamp":1627777843165,"uuid":"moqmEludJcMrVeCmIwVasQ","version":"1"}
{"action":{"alias":{"address":"N\u0000sourcecred\u0000discord\u0000MEMBER\u0000user\u0000610884157580771348\u0000","description":"discord/VladimirP#4200"},"identityId":"C9sGGSjXiLkD81eVMeqkqw","type":"ADD_ALIAS"},"ledgerTimestamp":1627777843165,"uuid":"fBi5l5kyecmJgnB5tPyztg","version":"1"}
{"action":{"identity":{"address":"N\u0000sourcecred\u0000core\u0000IDENTITY\u0000NuKU4wM4AUXvp2lCdxzKHg\u0000","aliases":[],"id":"NuKU4wM4AUXvp2lCdxzKHg","name":"Filip","subtype":"USER"},"type":"CREATE_IDENTITY"},"ledgerTimestamp":1627777843165,"uuid":"QypSbSYQlY7MqqR5rVf0SQ","version":"1"}
{"action":{"alias":{"address":"N\u0000sourcecred\u0000discord\u0000MEMBER\u0000user\u0000637649232349888512\u0000","description":"discord/Filip#2852"},"identityId":"NuKU4wM4AUXvp2lCdxzKHg","type":"ADD_ALIAS"},"ledgerTimestamp":1627777843165,"uuid":"Q0XpfmzsvqfW2sN7MVHj3w","version":"1"}
{"action":{"identity":{"address":"N\u0000sourcecred\u0000core\u0000IDENTITY\u0000Ot99muYgNAVV1F0haayruA\u0000","aliases":[],"id":"Ot99muYgNAVV1F0haayruA","name":"PeteOK","subtype":"USER"},"type":"CREATE_IDENTITY"},"ledgerTimestamp":1627777843166,"uuid":"J0hK3F3JxbZKGdNQxnVi6g","version":"1"}
{"action":{"alias":{"address":"N\u0000sourcecred\u0000discord\u0000MEMBER\u0000user\u0000697209843714621561\u0000","description":"discord/PeteOK#6774"},"identityId":"Ot99muYgNAVV1F0haayruA","type":"ADD_ALIAS"},"ledgerTimestamp":1627777843166,"uuid":"LVUJ6E9iQy8PHyXVTgAS5w","version":"1"}
{"action":{"identity":{"address":"N\u0000sourcecred\u0000core\u0000IDENTITY\u0000jbvJJMviXqyZpOU9vXb83Q\u0000","aliases":[],"id":"jbvJJMviXqyZpOU9vXb83Q","name":"Steve","subtype":"USER"},"type":"CREATE_IDENTITY"},"ledgerTimestamp":1627777843166,"uuid":"YeQ9bWQGP0YMUO7nJEHnJA","version":"1"}
{"action":{"alias":{"address":"N\u0000sourcecred\u0000discord\u0000MEMBER\u0000user\u0000706651429779013784\u0000","description":"discord/Steve#5925"},"identityId":"jbvJJMviXqyZpOU9vXb83Q","type":"ADD_ALIAS"},"ledgerTimestamp":1627777843166,"uuid":"f2YJk5V8xukeibijWIKCZQ","version":"1"}
{"action":{"identity":{"address":"N\u0000sourcecred\u0000core\u0000IDENTITY\u0000iLlL58vJY9lb39EpbXpCYQ\u0000","aliases":[],"id":"iLlL58vJY9lb39EpbXpCYQ","name":"jenniferevonne","subtype":"USER"},"type":"CREATE_IDENTITY"},"ledgerTimestamp":1627777843166,"uuid":"cye0nwdnY5xnXlJPtjLdYA","version":"1"}
{"action":{"alias":{"address":"N\u0000sourcecred\u0000discord\u0000MEMBER\u0000user\u0000706914757155880978\u0000","description":"discord/jenniferevonne#1995"},"identityId":"iLlL58vJY9lb39EpbXpCYQ","type":"ADD_ALIAS"},"ledgerTimestamp":1627777843167,"uuid":"iEvLLYc35q1LB2bnFj5rrQ","version":"1"}
{"action":{"identity":{"address":"N\u0000sourcecred\u0000core\u0000IDENTITY\u0000k9YbcvJMsdYWqdzsOYjSvQ\u0000","aliases":[],"id":"k9YbcvJMsdYWqdzsOYjSvQ","name":"tyler-wales","subtype":"USER"},"type":"CREATE_IDENTITY"},"ledgerTimestamp":1627777843167,"uuid":"xrwfpjMqt5T6ZFj4akDwdw","version":"1"}
{"action":{"alias":{"address":"N\u0000sourcecred\u0000discord\u0000MEMBER\u0000user\u0000713105321622634588\u0000","description":"discord/tyler.wales#0730"},"identityId":"k9YbcvJMsdYWqdzsOYjSvQ","type":"ADD_ALIAS"},"ledgerTimestamp":1627777843167,"uuid":"k9CdQIauNlL4RV8K7TekqQ","version":"1"}
{"action":{"identity":{"address":"N\u0000sourcecred\u0000core\u0000IDENTITY\u0000BpOekaaduy9iPHMBuByN9A\u0000","aliases":[],"id":"BpOekaaduy9iPHMBuByN9A","name":"CryptoPriex-1PP01-1PP02-1PP03-","subtype":"USER"},"type":"CREATE_IDENTITY"},"ledgerTimestamp":1627777843167,"uuid":"vlrFOhR1g32bA1mmCPNmhQ","version":"1"}
{"action":{"alias":{"address":"N\u0000sourcecred\u0000discord\u0000MEMBER\u0000user\u0000718736043649531926\u0000","description":"discord/CryptoPriex(1PP01,1PP02,1PP03)#7052"},"identityId":"BpOekaaduy9iPHMBuByN9A","type":"ADD_ALIAS"},"ledgerTimestamp":1627777843167,"uuid":"fWcw1zAZ8u52ZgVgLEHyYg","version":"1"}
{"action":{"identity":{"address":"N\u0000sourcecred\u0000core\u0000IDENTITY\u0000VbKdYw80gk4EqGP9Cletbg\u0000","aliases":[],"id":"VbKdYw80gk4EqGP9Cletbg","name":"Kudos","subtype":"BOT"},"type":"CREATE_IDENTITY"},"ledgerTimestamp":1627777843168,"uuid":"7Plp8eOIJCa3S8480O3Bog","version":"1"}
{"action":{"alias":{"address":"N\u0000sourcecred\u0000discord\u0000MEMBER\u0000bot\u0000719571683517792286\u0000","description":"discord/Kudos#9294"},"identityId":"VbKdYw80gk4EqGP9Cletbg","type":"ADD_ALIAS"},"ledgerTimestamp":1627777843168,"uuid":"wQNKRnmFL1uGOBilrMi6SA","version":"1"}
{"action":{"identity":{"address":"N\u0000sourcecred\u0000core\u0000IDENTITY\u0000YlqEErGFLXyH4KV29xtmPg\u0000","aliases":[],"id":"YlqEErGFLXyH4KV29xtmPg","name":"jamesdunseith","subtype":"USER"},"type":"CREATE_IDENTITY"},"ledgerTimestamp":1627777843168,"uuid":"aLzhRoI9qwzNSDxqUqhnZw","version":"1"}
{"action":{"alias":{"address":"N\u0000sourcecred\u0000discord\u0000MEMBER\u0000user\u0000730401371555233813\u0000","description":"discord/jamesdunseith#3315"},"identityId":"YlqEErGFLXyH4KV29xtmPg","type":"ADD_ALIAS"},"ledgerTimestamp":1627777843168,"uuid":"r6QSpvM6r7A2W6H3VozgGQ","version":"1"}
{"action":{"identity":{"address":"N\u0000sourcecred\u0000core\u0000IDENTITY\u0000UGGa23bnoDc9XoH9Wm3haQ\u0000","aliases":[],"id":"UGGa23bnoDc9XoH9Wm3haQ","name":"adosiawolf","subtype":"USER"},"type":"CREATE_IDENTITY"},"ledgerTimestamp":1627777843169,"uuid":"8ve5j74ESLwKkZ20dN2HZw","version":"1"}
{"action":{"alias":{"address":"N\u0000sourcecred\u0000discord\u0000MEMBER\u0000user\u0000742177542089211904\u0000","description":"discord/adosiawolf#8878"},"identityId":"UGGa23bnoDc9XoH9Wm3haQ","type":"ADD_ALIAS"},"ledgerTimestamp":1627777843169,"uuid":"U0uEDrkErzuB8nna0oXpzQ","version":"1"}
{"action":{"identity":{"address":"N\u0000sourcecred\u0000core\u0000IDENTITY\u00001VUkxCQS2crXsqPK2Do8XA\u0000","aliases":[],"id":"1VUkxCQS2crXsqPK2Do8XA","name":"Lauris--StakePool247---EU01-","subtype":"USER"},"type":"CREATE_IDENTITY"},"ledgerTimestamp":1627777843169,"uuid":"H3UWBX1oodGbhbcA3JAQcA","version":"1"}
{"action":{"alias":{"address":"N\u0000sourcecred\u0000discord\u0000MEMBER\u0000user\u0000742621110696149042\u0000","description":"discord/Lauris (StakePool247 | EU01)#4674"},"identityId":"1VUkxCQS2crXsqPK2Do8XA","type":"ADD_ALIAS"},"ledgerTimestamp":1627777843169,"uuid":"ow1zfRYlpcGJZRjrdjsr0Q","version":"1"}
{"action":{"identity":{"address":"N\u0000sourcecred\u0000core\u0000IDENTITY\u0000xg8G5otqlX3BhQUBVqsmdA\u0000","aliases":[],"id":"xg8G5otqlX3BhQUBVqsmdA","name":"newmindflow","subtype":"USER"},"type":"CREATE_IDENTITY"},"ledgerTimestamp":1627777843169,"uuid":"OmCX4A36fL6pewajFyjR0Q","version":"1"}
{"action":{"alias":{"address":"N\u0000sourcecred\u0000discord\u0000MEMBER\u0000user\u0000750155545243156499\u0000","description":"discord/newmindflow#0033"},"identityId":"xg8G5otqlX3BhQUBVqsmdA","type":"ADD_ALIAS"},"ledgerTimestamp":1627777843169,"uuid":"jUm9u3ONG6m5hNJN6xMYFA","version":"1"}
{"action":{"identity":{"address":"N\u0000sourcecred\u0000core\u0000IDENTITY\u0000A1lK89g2Xoi4fzXraks4TA\u0000","aliases":[],"id":"A1lK89g2Xoi4fzXraks4TA","name":"mercyA1","subtype":"USER"},"type":"CREATE_IDENTITY"},"ledgerTimestamp":1627777843169,"uuid":"E9aMpdP6k8xg9R36By9k3Q","version":"1"}
{"action":{"alias":{"address":"N\u0000sourcecred\u0000discord\u0000MEMBER\u0000user\u0000753397748430012496\u0000","description":"discord/mercyA1#1150"},"identityId":"A1lK89g2Xoi4fzXraks4TA","type":"ADD_ALIAS"},"ledgerTimestamp":1627777843169,"uuid":"c80g1iRGF9hGMWGsA2qIlA","version":"1"}
{"action":{"identity":{"address":"N\u0000sourcecred\u0000core\u0000IDENTITY\u0000Kf8IGTQ7bY5GXMMemBy68w\u0000","aliases":[],"id":"Kf8IGTQ7bY5GXMMemBy68w","name":"Juliane","subtype":"USER"},"type":"CREATE_IDENTITY"},"ledgerTimestamp":1627777843170,"uuid":"hGmuRWvWJZj3NzRj02ZZMw","version":"1"}
{"action":{"alias":{"address":"N\u0000sourcecred\u0000discord\u0000MEMBER\u0000user\u0000753740381962764339\u0000","description":"discord/Juliane#1968"},"identityId":"Kf8IGTQ7bY5GXMMemBy68w","type":"ADD_ALIAS"},"ledgerTimestamp":1627777843170,"uuid":"PKzvt9BzW5AlT3uWjwezfg","version":"1"}
{"action":{"identity":{"address":"N\u0000sourcecred\u0000core\u0000IDENTITY\u0000XsWUWJce1b6UD983UQs4IA\u0000","aliases":[],"id":"XsWUWJce1b6UD983UQs4IA","name":"Maria-Carmo369","subtype":"USER"},"type":"CREATE_IDENTITY"},"ledgerTimestamp":1627777843170,"uuid":"M2m7QXIy5Jxgqye6XJLoDQ","version":"1"}
{"action":{"alias":{"address":"N\u0000sourcecred\u0000discord\u0000MEMBER\u0000user\u0000753871027632734272\u0000","description":"discord/Maria Carmo369#0921"},"identityId":"XsWUWJce1b6UD983UQs4IA","type":"ADD_ALIAS"},"ledgerTimestamp":1627777843170,"uuid":"HQXPN3XEmoE5gWAlpALyIw","version":"1"}
{"action":{"identity":{"address":"N\u0000sourcecred\u0000core\u0000IDENTITY\u00006eS2JRlsWoNc585pZBYAXw\u0000","aliases":[],"id":"6eS2JRlsWoNc585pZBYAXw","name":"Lucio","subtype":"USER"},"type":"CREATE_IDENTITY"},"ledgerTimestamp":1627777843171,"uuid":"VuRgoMyNayfNN8NJuQjEzw","version":"1"}
{"action":{"alias":{"address":"N\u0000sourcecred\u0000discord\u0000MEMBER\u0000user\u0000759128031482216462\u0000","description":"discord/Lucio#3247"},"identityId":"6eS2JRlsWoNc585pZBYAXw","type":"ADD_ALIAS"},"ledgerTimestamp":1627777843171,"uuid":"iqygOY5pPabpD9SjkEl4VQ","version":"1"}
{"action":{"identity":{"address":"N\u0000sourcecred\u0000core\u0000IDENTITY\u0000kCAH64ubRo7jf326wBPpyg\u0000","aliases":[],"id":"kCAH64ubRo7jf326wBPpyg","name":"Steve-Lockhart","subtype":"USER"},"type":"CREATE_IDENTITY"},"ledgerTimestamp":1627777843171,"uuid":"0JmK8AluOQNfDdRl7xjpDA","version":"1"}
{"action":{"alias":{"address":"N\u0000sourcecred\u0000discord\u0000MEMBER\u0000user\u0000787747120094117949\u0000","description":"discord/Steve Lockhart#5327"},"identityId":"kCAH64ubRo7jf326wBPpyg","type":"ADD_ALIAS"},"ledgerTimestamp":1627777843171,"uuid":"ltnarRVPiQFo6E0ojGAecQ","version":"1"}
{"action":{"identity":{"address":"N\u0000sourcecred\u0000core\u0000IDENTITY\u0000R5TbPiAlFqFKRH7FMkqw3g\u0000","aliases":[],"id":"R5TbPiAlFqFKRH7FMkqw3g","name":"Dudi-Edri--ISR-","subtype":"USER"},"type":"CREATE_IDENTITY"},"ledgerTimestamp":1627777843172,"uuid":"ZsQOQNvZMaFyTdaAM0ebQw","version":"1"}
{"action":{"alias":{"address":"N\u0000sourcecred\u0000discord\u0000MEMBER\u0000user\u0000797609813441511476\u0000","description":"discord/Dudi Edri [ISR]#2054"},"identityId":"R5TbPiAlFqFKRH7FMkqw3g","type":"ADD_ALIAS"},"ledgerTimestamp":1627777843172,"uuid":"f3N152r8vGMns0YRH9yoxA","version":"1"}
{"action":{"identity":{"address":"N\u0000sourcecred\u0000core\u0000IDENTITY\u0000IWjbkuqPjmZBlUnwIRDtWA\u0000","aliases":[],"id":"IWjbkuqPjmZBlUnwIRDtWA","name":"DucTIGER","subtype":"USER"},"type":"CREATE_IDENTITY"},"ledgerTimestamp":1627777843173,"uuid":"cXimcn6QrajBZujWribxFw","version":"1"}
{"action":{"alias":{"address":"N\u0000sourcecred\u0000discord\u0000MEMBER\u0000user\u0000799094982735822858\u0000","description":"discord/DucTIGER#4232"},"identityId":"IWjbkuqPjmZBlUnwIRDtWA","type":"ADD_ALIAS"},"ledgerTimestamp":1627777843173,"uuid":"DAAKTm4qTj1x2MmEjJ8ZAg","version":"1"}
{"action":{"identity":{"address":"N\u0000sourcecred\u0000core\u0000IDENTITY\u0000sLGVYD01LeZKM6r9v5OXKQ\u0000","aliases":[],"id":"sLGVYD01LeZKM6r9v5OXKQ","name":"JoshF","subtype":"USER"},"type":"CREATE_IDENTITY"},"ledgerTimestamp":1627777843173,"uuid":"deUaXqV7DjR3a1GugizQWw","version":"1"}
{"action":{"alias":{"address":"N\u0000sourcecred\u0000discord\u0000MEMBER\u0000user\u0000801535365328404501\u0000","description":"discord/JoshF#2224"},"identityId":"sLGVYD01LeZKM6r9v5OXKQ","type":"ADD_ALIAS"},"ledgerTimestamp":1627777843173,"uuid":"i3GHjMJ31C3jWYIrF9GCPg","version":"1"}
{"action":{"identity":{"address":"N\u0000sourcecred\u0000core\u0000IDENTITY\u0000cph3Gb7c87yMoL6h9V1bBA\u0000","aliases":[],"id":"cph3Gb7c87yMoL6h9V1bBA","name":"tamagnaz","subtype":"USER"},"type":"CREATE_IDENTITY"},"ledgerTimestamp":1627777843173,"uuid":"wVLJDcxX2n9KLc2zO5UAxg","version":"1"}
{"action":{"alias":{"address":"N\u0000sourcecred\u0000discord\u0000MEMBER\u0000user\u0000801880051092029466\u0000","description":"discord/tamagnaz#4720"},"identityId":"cph3Gb7c87yMoL6h9V1bBA","type":"ADD_ALIAS"},"ledgerTimestamp":1627777843174,"uuid":"RqFWNavuYGfWOoLHDTYCyw","version":"1"}
{"action":{"identity":{"address":"N\u0000sourcecred\u0000core\u0000IDENTITY\u0000yLoESRjldv40fGC30qLoxQ\u0000","aliases":[],"id":"yLoESRjldv40fGC30qLoxQ","name":"Victor-Corcino","subtype":"USER"},"type":"CREATE_IDENTITY"},"ledgerTimestamp":1627777843174,"uuid":"hWzZJ7yXdzncx38xv6nwDA","version":"1"}
{"action":{"alias":{"address":"N\u0000sourcecred\u0000discord\u0000MEMBER\u0000user\u0000809126266979483689\u0000","description":"discord/Victor Corcino#9011"},"identityId":"yLoESRjldv40fGC30qLoxQ","type":"ADD_ALIAS"},"ledgerTimestamp":1627777843174,"uuid":"WRsKoI5dbJpl5m4gBwbOKA","version":"1"}
{"action":{"identity":{"address":"N\u0000sourcecred\u0000core\u0000IDENTITY\u0000tDAYpANDmGqBlwUwyrxpoA\u0000","aliases":[],"id":"tDAYpANDmGqBlwUwyrxpoA","name":"stephen-rowan","subtype":"USER"},"type":"CREATE_IDENTITY"},"ledgerTimestamp":1627777843174,"uuid":"IPywVecJ8cNO85QsRjqqoA","version":"1"}
{"action":{"alias":{"address":"N\u0000sourcecred\u0000discord\u0000MEMBER\u0000user\u0000815334780391915592\u0000","description":"discord/stephen.rowan#7396"},"identityId":"tDAYpANDmGqBlwUwyrxpoA","type":"ADD_ALIAS"},"ledgerTimestamp":1627777843174,"uuid":"z82iDc3ue1gCbpUBLign9w","version":"1"}
{"action":{"identity":{"address":"N\u0000sourcecred\u0000core\u0000IDENTITY\u0000O06VzeSQqYCMgyEt08Namg\u0000","aliases":[],"id":"O06VzeSQqYCMgyEt08Namg","name":"DominikTilman","subtype":"USER"},"type":"CREATE_IDENTITY"},"ledgerTimestamp":1627777843175,"uuid":"MkeH7YlOp5eW6yZX2O50ww","version":"1"}
{"action":{"alias":{"address":"N\u0000sourcecred\u0000discord\u0000MEMBER\u0000user\u0000816738307861250078\u0000","description":"discord/DominikTilman#0150"},"identityId":"O06VzeSQqYCMgyEt08Namg","type":"ADD_ALIAS"},"ledgerTimestamp":1627777843175,"uuid":"cpMhMEu3HaJkzi2i7o3Swg","version":"1"}
{"action":{"identity":{"address":"N\u0000sourcecred\u0000core\u0000IDENTITY\u0000fe2lAnIBjZzVraZGLG1EQg\u0000","aliases":[],"id":"fe2lAnIBjZzVraZGLG1EQg","name":"StefanMontalbetti","subtype":"USER"},"type":"CREATE_IDENTITY"},"ledgerTimestamp":1627777843175,"uuid":"TZ9ro3GM1WYxrqBLqS08Yg","version":"1"}
{"action":{"alias":{"address":"N\u0000sourcecred\u0000discord\u0000MEMBER\u0000user\u0000817800612266770473\u0000","description":"discord/StefanMontalbetti#9069"},"identityId":"fe2lAnIBjZzVraZGLG1EQg","type":"ADD_ALIAS"},"ledgerTimestamp":1627777843175,"uuid":"E4fnFjNd2UvTj0ypnGp0VA","version":"1"}
{"action":{"identity":{"address":"N\u0000sourcecred\u0000core\u0000IDENTITY\u0000jMEM57SZGD2ygbydkN3HzA\u0000","aliases":[],"id":"jMEM57SZGD2ygbydkN3HzA","name":"Ken-Adams--KEWW-","subtype":"USER"},"type":"CREATE_IDENTITY"},"ledgerTimestamp":1627777843175,"uuid":"mTbuqzckUwulipdKwoZcDw","version":"1"}
{"action":{"alias":{"address":"N\u0000sourcecred\u0000discord\u0000MEMBER\u0000user\u0000819273581707264062\u0000","description":"discord/Ken Adams (KEWW)#8362"},"identityId":"jMEM57SZGD2ygbydkN3HzA","type":"ADD_ALIAS"},"ledgerTimestamp":1627777843176,"uuid":"HQfpKsMW3dq9SbqdxJJYUQ","version":"1"}
{"action":{"identity":{"address":"N\u0000sourcecred\u0000core\u0000IDENTITY\u0000S1cd1HWSodLfQtGxw3qzXg\u0000","aliases":[],"id":"S1cd1HWSodLfQtGxw3qzXg","name":"FelixWeber","subtype":"USER"},"type":"CREATE_IDENTITY"},"ledgerTimestamp":1627777843176,"uuid":"CNZNyirt4YZwC4dFwYrQeA","version":"1"}
{"action":{"alias":{"address":"N\u0000sourcecred\u0000discord\u0000MEMBER\u0000user\u0000820728090778533928\u0000","description":"discord/FelixWeber#9839"},"identityId":"S1cd1HWSodLfQtGxw3qzXg","type":"ADD_ALIAS"},"ledgerTimestamp":1627777843176,"uuid":"gPrZWWu6eK9lnpmdZrhjyw","version":"1"}
{"action":{"identity":{"address":"N\u0000sourcecred\u0000core\u0000IDENTITY\u0000re0uzSBbU05zGqXoBgc78w\u0000","aliases":[],"id":"re0uzSBbU05zGqXoBgc78w","name":"JakobD","subtype":"USER"},"type":"CREATE_IDENTITY"},"ledgerTimestamp":1627777843176,"uuid":"7IeY9fqywwbR8fQqvT8Ypw","version":"1"}
{"action":{"alias":{"address":"N\u0000sourcecred\u0000discord\u0000MEMBER\u0000user\u0000824347473187045406\u0000","description":"discord/JakobD#2756"},"identityId":"re0uzSBbU05zGqXoBgc78w","type":"ADD_ALIAS"},"ledgerTimestamp":1627777843176,"uuid":"90FRNxfnv0Ksar9k7naBAA","version":"1"}
{"action":{"identity":{"address":"N\u0000sourcecred\u0000core\u0000IDENTITY\u0000MDJWz8tEyUe4FoceGvg1Yw\u0000","aliases":[],"id":"MDJWz8tEyUe4FoceGvg1Yw","name":"Token-Dreams","subtype":"USER"},"type":"CREATE_IDENTITY"},"ledgerTimestamp":1627777843177,"uuid":"mc5IWds2ULbsM0Xm4edoww","version":"1"}
{"action":{"alias":{"address":"N\u0000sourcecred\u0000discord\u0000MEMBER\u0000user\u0000829434301006872636\u0000","description":"discord/Token.Dreams#3124"},"identityId":"MDJWz8tEyUe4FoceGvg1Yw","type":"ADD_ALIAS"},"ledgerTimestamp":1627777843177,"uuid":"wxXApfXNsky4f0DvwswYnw","version":"1"}
{"action":{"identity":{"address":"N\u0000sourcecred\u0000core\u0000IDENTITY\u0000xWZXfdxMH93swFLigh4XIQ\u0000","aliases":[],"id":"xWZXfdxMH93swFLigh4XIQ","name":"Edi-Polonski--ISR-","subtype":"USER"},"type":"CREATE_IDENTITY"},"ledgerTimestamp":1627777843178,"uuid":"ARikFYQJRtdWsj5gigb3BQ","version":"1"}
{"action":{"alias":{"address":"N\u0000sourcecred\u0000discord\u0000MEMBER\u0000user\u0000835078768858234930\u0000","description":"discord/Edi Polonski [ISR]#8331"},"identityId":"xWZXfdxMH93swFLigh4XIQ","type":"ADD_ALIAS"},"ledgerTimestamp":1627777843178,"uuid":"u1uGFQxo297O8xY3azW0gw","version":"1"}
{"action":{"identity":{"address":"N\u0000sourcecred\u0000core\u0000IDENTITY\u0000ZS8HgPFWYW1EjgFZ3886Aw\u0000","aliases":[],"id":"ZS8HgPFWYW1EjgFZ3886Aw","name":"CatalystSourceCred","subtype":"BOT"},"type":"CREATE_IDENTITY"},"ledgerTimestamp":1627777843178,"uuid":"nYPnbU8h9fbuDh68zJA2Lg","version":"1"}
{"action":{"alias":{"address":"N\u0000sourcecred\u0000discord\u0000MEMBER\u0000bot\u0000865149365273362454\u0000","description":"discord/CatalystSourceCred#1980"},"identityId":"ZS8HgPFWYW1EjgFZ3886Aw","type":"ADD_ALIAS"},"ledgerTimestamp":1627777843178,"uuid":"f9QT14ClvOWlP09UkruQ3Q","version":"1"}
{"action":{"identity":{"address":"N\u0000sourcecred\u0000core\u0000IDENTITY\u0000S3oXjiejCjGr04VS0zPuoA\u0000","aliases":[],"id":"S3oXjiejCjGr04VS0zPuoA","name":"stephen","subtype":"USER"},"type":"CREATE_IDENTITY"},"ledgerTimestamp":1627777843178,"uuid":"YDUAwm0CxqAWzq4uvyNZZQ","version":"1"}
{"action":{"alias":{"address":"N\u0000sourcecred\u0000discord\u0000MEMBER\u0000user\u0000320352233332015109\u0000","description":"discord/stephen#5990"},"identityId":"S3oXjiejCjGr04VS0zPuoA","type":"ADD_ALIAS"},"ledgerTimestamp":1627777843179,"uuid":"5lDytJZiZ2GJHnqQ3WaF8A","version":"1"}
{"action":{"identity":{"address":"N\u0000sourcecred\u0000core\u0000IDENTITY\u0000SpoxgAImG0SLzCaUY4JYIQ\u0000","aliases":[],"id":"SpoxgAImG0SLzCaUY4JYIQ","name":"wolstaeb","subtype":"USER"},"type":"CREATE_IDENTITY"},"ledgerTimestamp":1627777843179,"uuid":"6EeLn6UL6vzyxlRPzzCLpg","version":"1"}
{"action":{"alias":{"address":"N\u0000sourcecred\u0000discord\u0000MEMBER\u0000user\u0000742318945373257832\u0000","description":"discord/wolstaeb#8130"},"identityId":"SpoxgAImG0SLzCaUY4JYIQ","type":"ADD_ALIAS"},"ledgerTimestamp":1627777843179,"uuid":"1VH7nlggec3GmS98QQ7TZQ","version":"1"}
{"action":{"identity":{"address":"N\u0000sourcecred\u0000core\u0000IDENTITY\u0000amaEpI97jkcG1e3Kqt346A\u0000","aliases":[],"id":"amaEpI97jkcG1e3Kqt346A","name":"SourceCred","subtype":"PROJECT"},"type":"CREATE_IDENTITY"},"ledgerTimestamp":1627777843548,"uuid":"Nd9sAoRDYEMEHa1zghXNyA","version":"1"}
{"action":{"identityId":"amaEpI97jkcG1e3Kqt346A","type":"TOGGLE_ACTIVATION"},"ledgerTimestamp":1627777843548,"uuid":"ZSeUyk5U2pjSMCNjaAN2MQ","version":"1"}
